CloudTrim/CloudTrim.py
CloudTrim/__init__.py
CloudTrim-0.0.1.dist-info/METADATA
CloudTrim-0.0.1.dist-info/WHEEL
CloudTrim-0.0.1.dist-info/top_level.txt
CloudTrim-0.0.1.dist-info/RECORD
