Metadata-Version: 2.1
Name: CloudTrim
Version: 0.0.1
Summary: for trimming online videos
Home-page: UNKNOWN
Author: Alvin Saini
Author-email: codewithalvin@gmail.com
License: MIT
Platform: UNKNOWN
Requires-Dist: moviepy
Requires-Dist: googledrivedownloader
